nostr_chatbot/__init__.py
nostr_chatbot/nostr/__init__.py
nostr_chatbot/nostr/_version.py
nostr_chatbot/nostr/bech32.py
nostr_chatbot/nostr/delegation.py
nostr_chatbot/nostr/event.py
nostr_chatbot/nostr/filter.py
nostr_chatbot/nostr/key.py
nostr_chatbot/nostr/message_pool.py
nostr_chatbot/nostr/message_type.py
nostr_chatbot/nostr/pow.py
nostr_chatbot/nostr/relay.py
nostr_chatbot/nostr/relay_manager.py
nostr_chatbot/nostr/request.py
nostr_chatbot/nostr/subscription.py
nostr_chatbot-0.1.0.dev2.dist-info/LICENSE.md
nostr_chatbot-0.1.0.dev2.dist-info/METADATA
nostr_chatbot-0.1.0.dev2.dist-info/WHEEL
nostr_chatbot-0.1.0.dev2.dist-info/top_level.txt
nostr_chatbot-0.1.0.dev2.dist-info/RECORD
